{"id": 1848, "fid": "1848", "name": "到目标元素的最小距离", "slug": "minimum-distance-to-the-target-element", "link": "https://leetcode.cn/problems/minimum-distance-to-the-target-element/description/", "percent": 0, "level": "Easy", "category": "algorithms", "en_name": "Minimum Distance to the Target Element", "cn_name": "到目标元素的最小距离", "desc": "<p>给你一个整数数组 <code>nums</code> （下标 <strong>从 0 开始</strong> 计数）以及两个整数 <code>target</code> 和 <code>start</code> ，请你找出一个下标 <code>i</code> ，满足 <code>nums[i] == target</code> 且 <code>abs(i - start)</code> <strong>最小化</strong> 。注意：<code>abs(x)</code> 表示 <code>x</code> 的绝对值。</p>\n\n<p>返回 <code>abs(i - start)</code> 。</p>\n\n<p>题目数据保证 <code>target</code> 存在于 <code>nums</code> 中。</p>\n\n<p> </p>\n\n<p><strong>示例 1：</strong></p>\n\n<pre>\n<strong>输入：</strong>nums = [1,2,3,4,5], target = 5, start = 3\n<strong>输出：</strong>1\n<strong>解释：</strong>nums[4] = 5 是唯一一个等于 target 的值，所以答案是 abs(4 - 3) = 1 。\n</pre>\n\n<p><strong>示例 2：</strong></p>\n\n<pre>\n<strong>输入：</strong>nums = [1], target = 1, start = 0\n<strong>输出：</strong>0\n<strong>解释：</strong>nums[0] = 1 是唯一一个等于 target 的值，所以答案是 abs(0 - 0) = 0 。\n</pre>\n\n<p><strong>示例 3：</strong></p>\n\n<pre>\n<strong>输入：</strong>nums = [1,1,1,1,1,1,1,1,1,1], target = 1, start = 0\n<strong>输出：</strong>0\n<strong>解释：</strong>nums 中的每个值都是 1 ，但 nums[0] 使 abs(i - start) 的结果得以最小化，所以答案是 abs(0 - 0) = 0 。\n</pre>\n\n<p> </p>\n\n<p><strong>提示：</strong></p>\n\n<ul>\n\t<li><code>1 <= nums.length <= 1000</code></li>\n\t<li><code>1 <= nums[i] <= 10<sup>4</sup></code></li>\n\t<li><code>0 <= start < nums.length</code></li>\n\t<li><code>target</code> 存在于 <code>nums</code> 中</li>\n</ul>\n", "templates": [{"value": "cpp", "text": "C++", "defaultCode": "class Solution {\npublic:\n    int getMinDistance(vector<int>& nums, int target, int start) {\n        \n    }\n};"}, {"value": "java", "text": "Java", "defaultCode": "class Solution {\n    public int getMinDistance(int[] nums, int target, int start) {\n        \n    }\n}"}, {"value": "python", "text": "Python", "defaultCode": "class Solution(object):\n    def getMinDistance(self, nums, target, start):\n        \"\"\"\n        :type nums: List[int]\n        :type target: int\n        :type start: int\n        :rtype: int\n        \"\"\"\n        "}, {"value": "python3", "text": "Python3", "defaultCode": "class Solution:\n    def getMinDistance(self, nums: List[int], target: int, start: int) -> int:\n        "}, {"value": "c", "text": "C", "defaultCode": "int getMinDistance(int* nums, int numsSize, int target, int start) {\n    \n}"}, {"value": "csharp", "text": "C#", "defaultCode": "public class Solution {\n    public int GetMinDistance(int[] nums, int target, int start) {\n        \n    }\n}"}, {"value": "javascript", "text": "JavaScript", "defaultCode": "/**\n * @param {number[]} nums\n * @param {number} target\n * @param {number} start\n * @return {number}\n */\nvar getMinDistance = function(nums, target, start) {\n    \n};"}, {"value": "typescript", "text": "TypeScript", "defaultCode": "function getMinDistance(nums: number[], target: number, start: number): number {\n    \n};"}, {"value": "php", "text": "PHP", "defaultCode": "class Solution {\n\n    /**\n     * @param Integer[] $nums\n     * @param Integer $target\n     * @param Integer $start\n     * @return Integer\n     */\n    function getMinDistance($nums, $target, $start) {\n        \n    }\n}"}, {"value": "swift", "text": "Swift", "defaultCode": "class Solution {\n    func getMinDistance(_ nums: [Int], _ target: Int, _ start: Int) -> Int {\n        \n    }\n}"}, {"value": "kotlin", "text": "Kotlin", "defaultCode": "class Solution {\n    fun getMinDistance(nums: IntArray, target: Int, start: Int): Int {\n        \n    }\n}"}, {"value": "dart", "text": "Dart", "defaultCode": "class Solution {\n  int getMinDistance(List<int> nums, int target, int start) {\n    \n  }\n}"}, {"value": "golang", "text": "Go", "defaultCode": "func getMinDistance(nums []int, target int, start int) int {\n    \n}"}, {"value": "ruby", "text": "Ruby", "defaultCode": "# @param {Integer[]} nums\n# @param {Integer} target\n# @param {Integer} start\n# @return {Integer}\ndef get_min_distance(nums, target, start)\n    \nend"}, {"value": "scala", "text": "Scala", "defaultCode": "object Solution {\n    def getMinDistance(nums: Array[Int], target: Int, start: Int): Int = {\n        \n    }\n}"}, {"value": "rust", "text": "Rust", "defaultCode": "impl Solution {\n    pub fn get_min_distance(nums: Vec<i32>, target: i32, start: i32) -> i32 {\n        \n    }\n}"}, {"value": "racket", "text": "Racket", "defaultCode": "(define/contract (get-min-distance nums target start)\n  (-> (listof exact-integer?) exact-integer? exact-integer? exact-integer?)\n  )"}, {"value": "erlang", "text": "Erlang", "defaultCode": "-spec get_min_distance(Nums :: [integer()], Target :: integer(), Start :: integer()) -> integer().\nget_min_distance(Nums, Target, Start) ->\n  ."}, {"value": "elixir", "text": "Elixir", "defaultCode": "defmodule Solution do\n  @spec get_min_distance(nums :: [integer], target :: integer, start :: integer) :: integer\n  def get_min_distance(nums, target, start) do\n    \n  end\nend"}, {"value": "cangjie", "text": "Cangjie", "defaultCode": "class Solution {\n    func getMinDistance(nums: Array<Int64>, target: Int64, start: Int64): Int64 {\n\n    }\n}"}]}