{"id": 2194, "fid": "2194", "name": "Excel 表中某个范围内的单元格", "slug": "cells-in-a-range-on-an-excel-sheet", "link": "https://leetcode.cn/problems/cells-in-a-range-on-an-excel-sheet/description/", "percent": 0, "level": "Easy", "category": "algorithms", "en_name": "Cells in a Range on an Excel Sheet", "cn_name": "Excel 表中某个范围内的单元格", "desc": "<p>Excel 表中的一个单元格 <code>(r, c)</code> 会以字符串 <code>\"&lt;col&gt;&lt;row&gt;\"</code> 的形式进行表示，其中：</p>\n\n<ul>\n\t<li><code>&lt;col&gt;</code> 即单元格的列号 <code>c</code> 。用英文字母表中的 <strong>字母</strong> 标识。\n\n\t<ul>\n\t\t<li>例如，第 <code>1</code> 列用 <code>'A'</code> 表示，第 <code>2</code> 列用 <code>'B'</code> 表示，第 <code>3</code> 列用 <code>'C'</code> 表示，以此类推。</li>\n\t</ul>\n\t</li>\n\t<li><code>&lt;row&gt;</code> 即单元格的行号 <code>r</code> 。第 <code>r</code> 行就用 <strong>整数</strong> <code>r</code> 标识。</li>\n</ul>\n\n<p>给你一个格式为 <code>\"&lt;col1&gt;&lt;row1&gt;:&lt;col2&gt;&lt;row2&gt;\"</code> 的字符串 <code>s</code> ，其中 <code>&lt;col1&gt;</code> 表示 <code>c1</code> 列，<code>&lt;row1&gt;</code> 表示 <code>r1</code> 行，<code>&lt;col2&gt;</code> 表示 <code>c2</code> 列，<code>&lt;row2&gt;</code> 表示 <code>r2</code> 行，并满足 <code>r1 &lt;= r2</code> 且 <code>c1 &lt;= c2</code> 。</p>\n\n<p>找出所有满足&nbsp;<code>r1 &lt;= x &lt;= r2</code> 且 <code>c1 &lt;= y &lt;= c2</code> 的单元格，并以列表形式返回。单元格应该按前面描述的格式用 <strong>字符串</strong> 表示，并以 <strong>非递减</strong> 顺序排列（先按列排，再按行排）。</p>\n\n<p>&nbsp;</p>\n\n<p><strong>示例 1：</strong></p>\n\n<p><img alt=\"\" src=\"https://assets.leetcode.com/uploads/2022/02/08/ex1drawio.png\" style=\"width: 250px; height: 160px;\" /></p>\n\n<pre>\n<strong>输入：</strong>s = \"K1:L2\"\n<strong>输出：</strong>[\"K1\",\"K2\",\"L1\",\"L2\"]\n<strong>解释：</strong>\n上图显示了列表中应该出现的单元格。\n红色箭头指示单元格的出现顺序。\n</pre>\n\n<p><strong>示例 2：</strong></p>\n\n<p><img alt=\"\" src=\"https://assets.leetcode.com/uploads/2022/02/09/exam2drawio.png\" style=\"width: 500px; height: 50px;\" /></p>\n\n<pre>\n<strong>输入：</strong>s = \"A1:F1\"\n<strong>输出：</strong>[\"A1\",\"B1\",\"C1\",\"D1\",\"E1\",\"F1\"]\n<strong>解释：</strong>\n上图显示了列表中应该出现的单元格。 \n红色箭头指示单元格的出现顺序。\n</pre>\n\n<p>&nbsp;</p>\n\n<p><strong>提示：</strong></p>\n\n<ul>\n\t<li><code>s.length == 5</code></li>\n\t<li><code>'A' &lt;= s[0] &lt;= s[3] &lt;= 'Z'</code></li>\n\t<li><code>'1' &lt;= s[1] &lt;= s[4] &lt;= '9'</code></li>\n\t<li><code>s</code> 由大写英文字母、数字、和 <code>':'</code> 组成</li>\n</ul>\n", "templates": [{"value": "cpp", "text": "C++", "defaultCode": "class Solution {\npublic:\n    vector<string> cellsInRange(string s) {\n        \n    }\n};"}, {"value": "java", "text": "Java", "defaultCode": "class Solution {\n    public List<String> cellsInRange(String s) {\n        \n    }\n}"}, {"value": "python", "text": "Python", "defaultCode": "class Solution(object):\n    def cellsInRange(self, s):\n        \"\"\"\n        :type s: str\n        :rtype: List[str]\n        \"\"\"\n        "}, {"value": "python3", "text": "Python3", "defaultCode": "class Solution:\n    def cellsInRange(self, s: str) -> List[str]:\n        "}, {"value": "c", "text": "C", "defaultCode": "/**\n * Note: The returned array must be malloced, assume caller calls free().\n */\nchar** cellsInRange(char* s, int* returnSize) {\n    \n}"}, {"value": "csharp", "text": "C#", "defaultCode": "public class Solution {\n    public IList<string> CellsInRange(string s) {\n        \n    }\n}"}, {"value": "javascript", "text": "JavaScript", "defaultCode": "/**\n * @param {string} s\n * @return {string[]}\n */\nvar cellsInRange = function(s) {\n    \n};"}, {"value": "typescript", "text": "TypeScript", "defaultCode": "function cellsInRange(s: string): string[] {\n    \n};"}, {"value": "php", "text": "PHP", "defaultCode": "class Solution {\n\n    /**\n     * @param String $s\n     * @return String[]\n     */\n    function cellsInRange($s) {\n        \n    }\n}"}, {"value": "swift", "text": "Swift", "defaultCode": "class Solution {\n    func cellsInRange(_ s: String) -> [String] {\n        \n    }\n}"}, {"value": "kotlin", "text": "Kotlin", "defaultCode": "class Solution {\n    fun cellsInRange(s: String): List<String> {\n        \n    }\n}"}, {"value": "dart", "text": "Dart", "defaultCode": "class Solution {\n  List<String> cellsInRange(String s) {\n    \n  }\n}"}, {"value": "golang", "text": "Go", "defaultCode": "func cellsInRange(s string) []string {\n    \n}"}, {"value": "ruby", "text": "Ruby", "defaultCode": "# @param {String} s\n# @return {String[]}\ndef cells_in_range(s)\n    \nend"}, {"value": "scala", "text": "Scala", "defaultCode": "object Solution {\n    def cellsInRange(s: String): List[String] = {\n        \n    }\n}"}, {"value": "rust", "text": "Rust", "defaultCode": "impl Solution {\n    pub fn cells_in_range(s: String) -> Vec<String> {\n        \n    }\n}"}, {"value": "racket", "text": "Racket", "defaultCode": "(define/contract (cells-in-range s)\n  (-> string? (listof string?))\n  )"}, {"value": "erlang", "text": "Erlang", "defaultCode": "-spec cells_in_range(S :: unicode:unicode_binary()) -> [unicode:unicode_binary()].\ncells_in_range(S) ->\n  ."}, {"value": "elixir", "text": "Elixir", "defaultCode": "defmodule Solution do\n  @spec cells_in_range(s :: String.t) :: [String.t]\n  def cells_in_range(s) do\n    \n  end\nend"}, {"value": "cangjie", "text": "Cangjie", "defaultCode": "class Solution {\n    func cellsInRange(s: String): ArrayList<String> {\n\n    }\n}"}]}