{"id": "面试题 03.05", "fid": "面试题 03.05", "name": "栈排序", "slug": "sort-of-stacks-lcci", "link": "https://leetcode.cn/problems/sort-of-stacks-lcci/description/", "percent": 0, "level": "Medium", "category": "algorithms", "en_name": "Sort of Stacks LCCI", "cn_name": "栈排序", "desc": "<p>栈排序。 编写程序，对栈进行排序使最小元素位于栈顶。最多只能使用一个其他的临时栈存放数据，但不得将元素复制到别的数据结构（如数组）中。该栈支持如下操作：<code>push</code>、<code>pop</code>、<code>peek</code> 和 <code>isEmpty</code>。当栈为空时，<code>peek</code>&nbsp;返回 -1。</p>\n\n<p><strong>示例 1：</strong></p>\n\n<pre>\n<strong> 输入</strong>：\n[\"SortedStack\", \"push\", \"push\", \"peek\", \"pop\", \"peek\"]\n[[], [1], [2], [], [], []]\n<strong> 输出</strong>：\n[null,null,null,1,null,2]\n</pre>\n\n<p><strong>示例 2：</strong></p>\n\n<pre>\n<strong> 输入</strong>： \n[\"SortedStack\", \"pop\", \"pop\", \"push\", \"pop\", \"isEmpty\"]\n[[], [], [], [1], [], []]\n<strong> 输出</strong>：\n[null,null,null,null,null,true]\n</pre>\n\n<p><strong>提示：</strong></p>\n\n<ol>\n\t<li>栈中的元素数目在[0, 5000]范围内。</li>\n</ol>\n", "templates": [{"value": "cpp", "text": "C++", "defaultCode": "class SortedStack {\npublic:\n    SortedStack() {\n        \n    }\n    \n    void push(int val) {\n        \n    }\n    \n    void pop() {\n        \n    }\n    \n    int peek() {\n        \n    }\n    \n    bool isEmpty() {\n        \n    }\n};\n\n/**\n * Your SortedStack object will be instantiated and called as such:\n * SortedStack* obj = new SortedStack();\n * obj->push(val);\n * obj->pop();\n * int param_3 = obj->peek();\n * bool param_4 = obj->isEmpty();\n */"}, {"value": "java", "text": "Java", "defaultCode": "class SortedStack {\n\n    public SortedStack() {\n        \n    }\n    \n    public void push(int val) {\n        \n    }\n    \n    public void pop() {\n        \n    }\n    \n    public int peek() {\n        \n    }\n    \n    public boolean isEmpty() {\n        \n    }\n}\n\n/**\n * Your SortedStack object will be instantiated and called as such:\n * SortedStack obj = new SortedStack();\n * obj.push(val);\n * obj.pop();\n * int param_3 = obj.peek();\n * boolean param_4 = obj.isEmpty();\n */"}, {"value": "python", "text": "Python", "defaultCode": "class SortedStack(object):\n\n    def __init__(self):\n        \n\n    def push(self, val):\n        \"\"\"\n        :type val: int\n        :rtype: None\n        \"\"\"\n        \n\n    def pop(self):\n        \"\"\"\n        :rtype: None\n        \"\"\"\n        \n\n    def peek(self):\n        \"\"\"\n        :rtype: int\n        \"\"\"\n        \n\n    def isEmpty(self):\n        \"\"\"\n        :rtype: bool\n        \"\"\"\n        \n\n\n# Your SortedStack object will be instantiated and called as such:\n# obj = SortedStack()\n# obj.push(val)\n# obj.pop()\n# param_3 = obj.peek()\n# param_4 = obj.isEmpty()"}, {"value": "python3", "text": "Python3", "defaultCode": "class SortedStack:\n\n    def __init__(self):\n        \n\n    def push(self, val: int) -> None:\n        \n\n    def pop(self) -> None:\n        \n\n    def peek(self) -> int:\n        \n\n    def isEmpty(self) -> bool:\n        \n\n\n# Your SortedStack object will be instantiated and called as such:\n# obj = SortedStack()\n# obj.push(val)\n# obj.pop()\n# param_3 = obj.peek()\n# param_4 = obj.isEmpty()"}, {"value": "c", "text": "C", "defaultCode": "\n\n\ntypedef struct {\n    \n} SortedStack;\n\n\nSortedStack* sortedStackCreate() {\n    \n}\n\nvoid sortedStackPush(SortedStack* obj, int val) {\n    \n}\n\nvoid sortedStackPop(SortedStack* obj) {\n    \n}\n\nint sortedStackPeek(SortedStack* obj) {\n    \n}\n\nbool sortedStackIsEmpty(SortedStack* obj) {\n    \n}\n\nvoid sortedStackFree(SortedStack* obj) {\n    \n}\n\n/**\n * Your SortedStack struct will be instantiated and called as such:\n * SortedStack* obj = sortedStackCreate();\n * sortedStackPush(obj, val);\n \n * sortedStackPop(obj);\n \n * int param_3 = sortedStackPeek(obj);\n \n * bool param_4 = sortedStackIsEmpty(obj);\n \n * sortedStackFree(obj);\n*/"}, {"value": "csharp", "text": "C#", "defaultCode": "public class SortedStack {\n\n    public SortedStack() {\n        \n    }\n    \n    public void Push(int val) {\n        \n    }\n    \n    public void Pop() {\n        \n    }\n    \n    public int Peek() {\n        \n    }\n    \n    public bool IsEmpty() {\n        \n    }\n}\n\n/**\n * Your SortedStack object will be instantiated and called as such:\n * SortedStack obj = new SortedStack();\n * obj.Push(val);\n * obj.Pop();\n * int param_3 = obj.Peek();\n * bool param_4 = obj.IsEmpty();\n */"}, {"value": "javascript", "text": "JavaScript", "defaultCode": "\nvar SortedStack = function() {\n    \n};\n\n/** \n * @param {number} val\n * @return {void}\n */\nSortedStack.prototype.push = function(val) {\n    \n};\n\n/**\n * @return {void}\n */\nSortedStack.prototype.pop = function() {\n    \n};\n\n/**\n * @return {number}\n */\nSortedStack.prototype.peek = function() {\n    \n};\n\n/**\n * @return {boolean}\n */\nSortedStack.prototype.isEmpty = function() {\n    \n};\n\n/** \n * Your SortedStack object will be instantiated and called as such:\n * var obj = new SortedStack()\n * obj.push(val)\n * obj.pop()\n * var param_3 = obj.peek()\n * var param_4 = obj.isEmpty()\n */"}, {"value": "typescript", "text": "TypeScript", "defaultCode": "class SortedStack {\n    constructor() {\n        \n    }\n\n    push(val: number): void {\n        \n    }\n\n    pop(): void {\n        \n    }\n\n    peek(): number {\n        \n    }\n\n    isEmpty(): boolean {\n        \n    }\n}\n\n/**\n * Your SortedStack object will be instantiated and called as such:\n * var obj = new SortedStack()\n * obj.push(val)\n * obj.pop()\n * var param_3 = obj.peek()\n * var param_4 = obj.isEmpty()\n */"}, {"value": "php", "text": "PHP", "defaultCode": "class SortedStack {\n    /**\n     */\n    function __construct() {\n        \n    }\n  \n    /**\n     * @param Integer $val\n     * @return NULL\n     */\n    function push($val) {\n        \n    }\n  \n    /**\n     * @return NULL\n     */\n    function pop() {\n        \n    }\n  \n    /**\n     * @return Integer\n     */\n    function peek() {\n        \n    }\n  \n    /**\n     * @return Boolean\n     */\n    function isEmpty() {\n        \n    }\n}\n\n/**\n * Your SortedStack object will be instantiated and called as such:\n * $obj = SortedStack();\n * $obj->push($val);\n * $obj->pop();\n * $ret_3 = $obj->peek();\n * $ret_4 = $obj->isEmpty();\n */"}, {"value": "swift", "text": "Swift", "defaultCode": "\nclass SortedStack {\n\n    init() {\n        \n    }\n    \n    func push(_ val: Int) {\n        \n    }\n    \n    func pop() {\n        \n    }\n    \n    func peek() -> Int {\n        \n    }\n    \n    func isEmpty() -> Bool {\n        \n    }\n}\n\n/**\n * Your SortedStack object will be instantiated and called as such:\n * let obj = SortedStack()\n * obj.push(val)\n * obj.pop()\n * let ret_3: Int = obj.peek()\n * let ret_4: Bool = obj.isEmpty()\n */"}, {"value": "kotlin", "text": "Kotlin", "defaultCode": "class SortedStack() {\n\n    fun push(`val`: Int) {\n        \n    }\n\n    fun pop() {\n        \n    }\n\n    fun peek(): Int {\n        \n    }\n\n    fun isEmpty(): Boolean {\n        \n    }\n\n}\n\n/**\n * Your SortedStack object will be instantiated and called as such:\n * var obj = SortedStack()\n * obj.push(`val`)\n * obj.pop()\n * var param_3 = obj.peek()\n * var param_4 = obj.isEmpty()\n */"}, {"value": "dart", "text": "Dart", "defaultCode": "class SortedStack {\n\n  SortedStack() {\n    \n  }\n  \n  void push(int val) {\n    \n  }\n  \n  void pop() {\n    \n  }\n  \n  int peek() {\n    \n  }\n  \n  bool isEmpty() {\n    \n  }\n}\n\n/**\n * Your SortedStack object will be instantiated and called as such:\n * SortedStack obj = SortedStack();\n * obj.push(val);\n * obj.pop();\n * int param3 = obj.peek();\n * bool param4 = obj.isEmpty();\n */"}, {"value": "golang", "text": "Go", "defaultCode": "type SortedStack struct {\n    \n}\n\n\nfunc Constructor() SortedStack {\n    \n}\n\n\nfunc (this *SortedStack) Push(val int)  {\n    \n}\n\n\nfunc (this *SortedStack) Pop()  {\n    \n}\n\n\nfunc (this *SortedStack) Peek() int {\n    \n}\n\n\nfunc (this *SortedStack) IsEmpty() bool {\n    \n}\n\n\n/**\n * Your SortedStack object will be instantiated and called as such:\n * obj := Constructor();\n * obj.Push(val);\n * obj.Pop();\n * param_3 := obj.Peek();\n * param_4 := obj.IsEmpty();\n */"}, {"value": "ruby", "text": "Ruby", "defaultCode": "class SortedStack\n    def initialize()\n        \n    end\n\n\n=begin\n    :type val: Integer\n    :rtype: Void\n=end\n    def push(val)\n        \n    end\n\n\n=begin\n    :rtype: Void\n=end\n    def pop()\n        \n    end\n\n\n=begin\n    :rtype: Integer\n=end\n    def peek()\n        \n    end\n\n\n=begin\n    :rtype: Boolean\n=end\n    def is_empty()\n        \n    end\n\n\nend\n\n# Your SortedStack object will be instantiated and called as such:\n# obj = SortedStack.new()\n# obj.push(val)\n# obj.pop()\n# param_3 = obj.peek()\n# param_4 = obj.is_empty()"}, {"value": "scala", "text": "Scala", "defaultCode": "class SortedStack() {\n\n    def push(`val`: Int): Unit = {\n        \n    }\n\n    def pop(): Unit = {\n        \n    }\n\n    def peek(): Int = {\n        \n    }\n\n    def isEmpty(): Boolean = {\n        \n    }\n\n}\n\n/**\n * Your SortedStack object will be instantiated and called as such:\n * val obj = new SortedStack()\n * obj.push(`val`)\n * obj.pop()\n * val param_3 = obj.peek()\n * val param_4 = obj.isEmpty()\n */"}, {"value": "rust", "text": "Rust", "defaultCode": "struct SortedStack {\n\n}\n\n\n/** \n * `&self` means the method takes an immutable reference.\n * If you need a mutable reference, change it to `&mut self` instead.\n */\nimpl SortedStack {\n\n    fn new() -> Self {\n        \n    }\n    \n    fn push(&self, val: i32) {\n        \n    }\n    \n    fn pop(&self) {\n        \n    }\n    \n    fn peek(&self) -> i32 {\n        \n    }\n    \n    fn is_empty(&self) -> bool {\n        \n    }\n}\n\n/**\n * Your SortedStack object will be instantiated and called as such:\n * let obj = SortedStack::new();\n * obj.push(val);\n * obj.pop();\n * let ret_3: i32 = obj.peek();\n * let ret_4: bool = obj.is_empty();\n */"}, {"value": "racket", "text": "Racket", "defaultCode": "(define sorted-stack%\n  (class object%\n    (super-new)\n    \n    (init-field)\n    \n    ; push : exact-integer? -> void?\n    (define/public (push val)\n      )\n    ; pop : -> void?\n    (define/public (pop)\n      )\n    ; peek : -> exact-integer?\n    (define/public (peek)\n      )\n    ; is-empty : -> boolean?\n    (define/public (is-empty)\n      )))\n\n;; Your sorted-stack% object will be instantiated and called as such:\n;; (define obj (new sorted-stack%))\n;; (send obj push val)\n;; (send obj pop)\n;; (define param_3 (send obj peek))\n;; (define param_4 (send obj is-empty))"}, {"value": "erlang", "text": "Erlang", "defaultCode": "-spec sorted_stack_init_() -> any().\nsorted_stack_init_() ->\n  .\n\n-spec sorted_stack_push(Val :: integer()) -> any().\nsorted_stack_push(Val) ->\n  .\n\n-spec sorted_stack_pop() -> any().\nsorted_stack_pop() ->\n  .\n\n-spec sorted_stack_peek() -> integer().\nsorted_stack_peek() ->\n  .\n\n-spec sorted_stack_is_empty() -> boolean().\nsorted_stack_is_empty() ->\n  .\n\n\n%% Your functions will be called as such:\n%% sorted_stack_init_(),\n%% sorted_stack_push(Val),\n%% sorted_stack_pop(),\n%% Param_3 = sorted_stack_peek(),\n%% Param_4 = sorted_stack_is_empty(),\n\n%% sorted_stack_init_ will be called before every test case, in which you can do some necessary initializations."}, {"value": "elixir", "text": "Elixir", "defaultCode": "defmodule SortedStack do\n  @spec init_() :: any\n  def init_() do\n    \n  end\n\n  @spec push(val :: integer) :: any\n  def push(val) do\n    \n  end\n\n  @spec pop() :: any\n  def pop() do\n    \n  end\n\n  @spec peek() :: integer\n  def peek() do\n    \n  end\n\n  @spec is_empty() :: boolean\n  def is_empty() do\n    \n  end\nend\n\n# Your functions will be called as such:\n# SortedStack.init_()\n# SortedStack.push(val)\n# SortedStack.pop()\n# param_3 = SortedStack.peek()\n# param_4 = SortedStack.is_empty()\n\n# SortedStack.init_ will be called before every test case, in which you can do some necessary initializations."}, {"value": "cangjie", "text": "Cangjie", "defaultCode": "class SortedStack {\n    init() {\n\n    }\n    \n    func push(val: Int64): Unit {\n\n    }\n    \n    func pop(): Unit {\n\n    }\n    \n    func peek(): Int64 {\n\n    }\n    \n    func isEmpty(): Bool {\n\n    }\n}\n\n/**\n * Your SortedStack object will be instantiated and called as such:\n * let obj: SortedStack = SortedStack()\n * obj.push(val)\n * obj.pop()\n * let param_3 = obj.peek()\n * let param_4 = obj.isEmpty()\n */"}]}